odoo10_addon_sequence_date_range-10.0.1.0.0.99.dev5-py3.8-nspkg.pth
odoo/addons/sequence_date_range/README.rst
odoo/addons/sequence_date_range/__init__.py
odoo/addons/sequence_date_range/__manifest__.py
odoo/addons/sequence_date_range/demo/ir_sequence.xml
odoo/addons/sequence_date_range/i18n/sequence_date_range.pot
odoo/addons/sequence_date_range/models/__init__.py
odoo/addons/sequence_date_range/models/ir_sequence.py
odoo/addons/sequence_date_range/models/ir_sequence_date_range.py
odoo/addons/sequence_date_range/readme/CONTRIBUTORS.rst
odoo/addons/sequence_date_range/readme/DESCRIPTION.rst
odoo/addons/sequence_date_range/static/description/icon.png
odoo/addons/sequence_date_range/static/description/index.html
odoo/addons/sequence_date_range/tests/__init__.py
odoo/addons/sequence_date_range/tests/test_ir_sequence_date_range.py
odoo/addons/sequence_date_range/views/ir_sequence.xml
odoo10_addon_sequence_date_range-10.0.1.0.0.99.dev5.dist-info/METADATA
odoo10_addon_sequence_date_range-10.0.1.0.0.99.dev5.dist-info/WHEEL
odoo10_addon_sequence_date_range-10.0.1.0.0.99.dev5.dist-info/namespace_packages.txt
odoo10_addon_sequence_date_range-10.0.1.0.0.99.dev5.dist-info/top_level.txt
odoo10_addon_sequence_date_range-10.0.1.0.0.99.dev5.dist-info/RECORD
