Metadata-Version: 2.1
Name: odoo10-addon-sequence-date-range
Version: 10.0.1.0.0.99.dev5
Summary: Module used to use the year of the date_to into sequences (instead of date_from)
Home-page: https://github.com/OCA/server-tools
Author: ACSONE SA/NV,Odoo Community Association (OCA)
Author-email: support@odoo-community.org
License: AGPL-3
Platform: UNKNOWN
Classifier: Programming Language :: Python
Classifier: Framework :: Odoo
Classifier: Framework :: Odoo :: 10.0
Classifier: License :: OSI Approved :: GNU Affero General Public License v3
Requires-Python: ~=2.7
Requires-Dist: odoo <10.1dev,>=10.0
